task1/rom.sv
module rom #(
	parameter  ADDRESS_WIDTH = 8,
			   DATA_WIDTH = 8
)(
	input logic                         clk,
    input logic     [ADDRESS_WIDTH-1:0] addr,
	output logic    [DATA_WIDTH-1:0]    dout
);

// initiate rom array with 2^ADDRESS_WIDTH elements.
// each element is size DATA_WIDTH
logic [DATA_WIDTH-1:0] rom_array [(2**ADDRESS_WIDTH)-1:0];

initial begin
		$display("Loading the rom.");
		$readmemh("sinerom.mem", rom_array);
end;

always_ff @(posedge clk)
	dout <= rom_array [addr];

endmodule

task1/counter.sv
module counter # (
    parameter WIDTH = 8
) (
    input logic rst,
    input logic en,
    input logic clk,
    input logic     [WIDTH-1:0] incr, // increment
    output logic    [WIDTH-1:0] count
);

always_ff @ (posedge clk)
    if (en)
        if (rst) count <= {WIDTH{1'b0}};
        else count <= count + incr;
endmodule

task2/sinegen.sv
module sinegen #(
    parameter   DATA_WIDTH = 8,
                ADDR_WIDTH = 8
) (
    input logic rst,
    input logic en,
    input logic clk,
    input logic     [DATA_WIDTH-1:0] incr,
    output logic    [DATA_WIDTH-1:0] dout
);

    logic [ADDR_WIDTH-1:0] addr_wire; // internal link between counter & rom addr

counter romCounter (
    .rst (rst),
    .en (en),
    .clk (clk),
    .incr (incr),
    .count (addr_wire)
);

rom sineRom (
    .clk (clk),
    .addr (addr_wire),
    .dout (dout)
);

endmodule

task1/sinegen.vcd
$version Generated by VerilatedVcd $end
$date Thu Oct 24 12:49:53 2024 $end
$timescale 1ps $end

 $scope module TOP $end
  $var wire  1 % clk $end
  $var wire  8 ' dout [7:0] $end
  $var wire  1 $ en $end
  $var wire  8 & incr [7:0] $end
  $var wire  1 # rst $end
  $scope module sinegen $end
   $var wire 32 ) ADDR_WIDTH [31:0] $end
   $var wire 32 ) DATA_WIDTH [31:0] $end
   $var wire  8 ( addr_wire [7:0] $end
   $var wire  1 % clk $end
   $var wire  8 ' dout [7:0] $end
   $var wire  1 $ en $end
   $var wire  8 & incr [7:0] $end
   $var wire  1 # rst $end
   $scope module romCounter $end
    $var wire 32 ) WIDTH [31:0] $end
    $var wire  1 % clk $end
    $var wire  8 ( count [7:0] $end
    $var wire  1 $ en $end
    $var wire  8 & incr [7:0] $end
    $var wire  1 # rst $end
   $upscope $end
   $scope module sineRom $end
    $var wire 32 ) ADDRESS_WIDTH [31:0] $end
    $var wire 32 ) DATA_WIDTH [31:0] $end
    $var wire  8 ( addr [7:0] $end
    $var wire  1 % clk $end
    $var wire  8 ' dout [7:0] $end
   $upscope $end
  $upscope $end
 $upscope $end
$enddefinitions $end


#0
0#
1$
1%
b00000101 &
b00000000 '
b00000000 (
b00000000000000000000000000001000 )
#1
0%
#2
1%
b11111110 '
b00000101 (
#3
0%
#4
1%
b11111101 '
b00001010 (
#5
0%
#6
1%
b11111010 '
b00001111 (
#7
0%
#8
1%
b11110101 '
b00010100 (
#9
0%
#10
1%
b11101111 '
b00011001 (
#11
0%
#12
1%
b11100110 '
b00011110 (
#13
0%
#14
1%
b11011101 '
b00100011 (
#15
0%
#16
1%
b11010001 '
b00101000 (
#17
0%
#18
1%
b11000101 '
b00101101 (
#19
0%
#20
1%
b10111000 '
b00110010 (
#21
0%
#22
1%
b10101001 '
b00110111 (
#23
0%
#24
1%
b10011010 '
b00111100 (
#25
0%
#26
1%
b10001011 '
b01000001 (
#27
0%
#28
1%
b01111011 '
b01000110 (
#29
0%
#30
1%
b01101100 '
b01001011 (
#31
0%
#32
1%
b01011101 '
b01010000 (
#33
0%
#34
1%
b01001110 '
b01010101 (
#35
0%
#36
1%
b01000000 '
b01011010 (
#37
0%
#38
1%
b00110011 '
b01011111 (
#39
0%
#40
1%
b00100111 '
b01100100 (
#41
0%
#42
1%
b00011100 '
b01101001 (
#43
0%
#44
1%
b00010011 '
b01101110 (
#45
0%
#46
1%
b00001100 '
b01110011 (
#47
0%
#48
1%
b00000110 '
b01111000 (
#49
0%
#50
1%
b00000010 '
b01111101 (
#51
0%
#52
1%
b00000000 '
b10000010 (
#53
0%
#54
1%
b10000111 (
#55
0%
#56
1%
b00000001 '
b10001100 (
#57
0%
#58
1%
b00000101 '
b10010001 (
#59
0%
#60
1%
b00001010 '
b10010110 (
#61
0%
#62
1%
b00010010 '
b10011011 (
#63
0%
#64
1%
b00011010 '
b10100000 (
#65
0%
#66
1%
b00100101 '
b10100101 (
#67
0%
#68
1%
b00110000 '
b10101010 (
#69
0%
#70
1%
b00111101 '
b10101111 (
#71
0%
#72
1%
b01001011 '
b10110100 (
#73
0%
#74
1%
b01011010 '
b10111001 (
#75
0%
#76
1%
b01101001 '
b10111110 (
#77
0%
#78
1%
b01111000 '
b11000011 (
#79
0%
#80
1%
b10001000 '
b11001000 (
#81
0%
#82
1%
b10010111 '
b11001101 (
#83
0%
#84
1%
b10100110 '
b11010010 (
#85
0%
#86
1%
b10110101 '
b11010111 (
#87
0%
#88
1%
b11000010 '
b11011100 (
#89
0%
#90
1%
b11001111 '
b11100001 (
#91
0%
#92
1%
b11011010 '
b11100110 (
#93
0%
#94
1%
b11100101 '
b11101011 (
#95
0%
#96
1%
b11101101 '
b11110000 (
#97
0%
#98
1%
b11110100 '
b11110101 (
#99
0%
#100
1%
b11111001 '
b11111010 (
#101
0%
#102
1%
b11111100 '
b11111111 (
#103
0%
#104
1%
b11111101 '
b00000100 (
#105
0%
#106
1%
b00001001 (
#107
0%
#108
1%
b11111010 '
b00001110 (
#109
0%
#110
1%
b11110110 '
b00010011 (
#111
0%
#112
1%
b11110000 '
b00011000 (
#113
0%
#114
1%
b11101000 '
b00011101 (
#115
0%
#116
1%
b11011111 '
b00100010 (
#117
0%
#118
1%
b11010100 '
b00100111 (
#119
0%
#120
1%
b11001000 '
b00101100 (
#121
0%
#122
1%
b10111010 '
b00110001 (
#123
0%
#124
1%
b10101100 '
b00110110 (
#125
0%
#126
1%
b10011101 '
b00111011 (
#127
0%
#128
1%
b10001110 '
b01000000 (
#129
0%
#130
1%
b01111110 '
b01000101 (
#131
0%
#132
1%
b01101111 '
b01001010 (
#133
0%
#134
1%
b01100000 '
b01001111 (
#135
0%
#136
1%
b01010001 '
b01010100 (
#137
0%
#138
1%
b01000011 '
b01011001 (
#139
0%
#140
1%
b00110101 '
b01011110 (
#141
0%
#142
1%
b00101001 '
b01100011 (
#143
0%
#144
1%
b00011110 '
b01101000 (
#145
0%
#146
1%
b00010101 '
b01101101 (
#147
0%
#148
1%
b00001101 '
b01110010 (
#149
0%
#150
1%
b00000111 '
b01110111 (
#151
0%
#152
1%
b00000011 '
b01111100 (
#153
0%
#154
1%
b00000000 '
b10000001 (
#155
0%
#156
1%
b10000110 (
#157
0%
#158
1%
b00000001 '
b10001011 (
#159
0%
#160
1%
b00000100 '
b10010000 (
#161
0%
#162
1%
b00001001 '
b10010101 (
#163
0%
#164
1%
b00010000 '
b10011010 (
#165
0%
#166
1%
b00011000 '
b10011111 (
#167
0%
#168
1%
b00100011 '
b10100100 (
#169
0%
#170
1%
b00101110 '
b10101001 (
#171
0%
#172
1%
b00111011 '
b10101110 (
#173
0%
#174
1%
b01001000 '
b10110011 (
#175
0%
#176
1%
b01010111 '
b10111000 (
#177
0%
#178
1%
b01100110 '
b10111101 (
#179
0%
#180
1%
b01110101 '
b11000010 (
#181
0%
#182
1%
b10000101 '
b11000111 (
#183
0%
#184
1%
b10010100 '
b11001100 (
#185
0%
#186
1%
b10100011 '
b11010001 (
#187
0%
#188
1%
b10110010 '
b11010110 (
#189
0%
#190
1%
b11000000 '
b11011011 (
#191
0%
#192
1%
b11001101 '
b11100000 (
#193
0%
#194
1%
b11011000 '
b11100101 (
#195
0%
#196
1%
b11100011 '
b11101010 (
#197
0%
#198
1%
b11101011 '
b11101111 (
#199
0%
#200
1%
b11110011 '
b11110100 (
#201
0%
#202
1%
b11111000 '
b11111001 (
#203
0%
#204
1%
b11111100 '
b11111110 (
#205
0%
#206
1%
b11111101 '
b00000011 (
#207
0%
#208
1%
b00001000 (
#209
0%
#210
1%
b11111011 '
b00001101 (
#211
0%
#212
1%
b11110111 '
b00010010 (
#213
0%
#214
1%
b11110001 '
b00010111 (
#215
0%
#216
1%
b11101010 '
b00011100 (
#217
0%
#218
1%
b11100001 '
b00100001 (
#219
0%
#220
1%
b11010110 '
b00100110 (
#221
0%
#222
1%
b11001010 '
b00101011 (
#223
0%
#224
1%
b10111101 '
b00110000 (
#225
0%
#226
1%
b10101111 '
b00110101 (
#227
0%
#228
1%
b10100000 '
b00111010 (
#229
0%
#230
1%
b10010001 '
b00111111 (
#231
0%
#232
1%
b10000010 '
b01000100 (
#233
0%
#234
1%
b01110010 '
b01001001 (
#235
0%
#236
1%
b01100011 '
b01001110 (
#237
0%
#238
1%
b01010100 '
b01010011 (
#239
0%
#240
1%
b01000101 '
b01011000 (
#241
0%
#242
1%
b00111000 '
b01011101 (
#243
0%
#244
1%
b00101100 '
b01100010 (
#245
0%
#246
1%
b00100000 '
b01100111 (
#247
0%
#248
1%
b00010111 '
b01101100 (
#249
0%
#250
1%
b00001110 '
b01110001 (
#251
0%
#252
1%
b00001000 '
b01110110 (
#253
0%
#254
1%
b00000011 '
b01111011 (
#255
0%
#256
1%
b00000000 '
b10000000 (
#257
0%
#258
1%
b10000101 (
#259
0%
#260
1%
b10001010 (
#261
0%
#262
1%
b00000011 '
b10001111 (
#263
0%
#264
1%
b00001000 '
b10010100 (
#265
0%
#266
1%
b00001110 '
b10011001 (
#267
0%
#268
1%
b00010111 '
b10011110 (
#269
0%
#270
1%
b00100000 '
b10100011 (
#271
0%
#272
1%
b00101100 '
b10101000 (
#273
0%
#274
1%
b00111000 '
b10101101 (
#275
0%
#276
1%
b01000101 '
b10110010 (
#277
0%
#278
1%
b01010100 '
b10110111 (
#279
0%
#280
1%
b01100011 '
b10111100 (
#281
0%
#282
1%
b01110010 '
b11000001 (
#283
0%
#284
1%
b10000010 '
b11000110 (
#285
0%
#286
1%
b10010001 '
b11001011 (
#287
0%
#288
1%
b10100000 '
b11010000 (
#289
0%
#290
1%
b10101111 '
b11010101 (
#291
0%
#292
1%
b10111101 '
b11011010 (
#293
0%
#294
1%
b11001010 '
b11011111 (
#295
0%
#296
1%
b11010110 '
b11100100 (
#297
0%
#298
1%
b11100001 '
b11101001 (
#299
0%
#300
1%
b11101010 '
b11101110 (
#301
0%
#302
1%
b11110001 '
b11110011 (
#303
0%
#304
1%
b11110111 '
b11111000 (
#305
0%
#306
1%
b11111011 '
b11111101 (
#307
0%
#308
1%
b11111101 '
b00000010 (
#309
0%
#310
1%
b00000111 (
#311
0%
#312
1%
b11111100 '
b00001100 (
#313
0%
#314
1%
b11111000 '
b00010001 (
#315
0%
#316
1%
b11110011 '
b00010110 (
#317
0%
#318
1%
b11101011 '
b00011011 (
#319
0%
#320
1%
b11100011 '
b00100000 (
#321
0%
#322
1%
b11011000 '
b00100101 (
#323
0%
#324
1%
b11001101 '
b00101010 (
#325
0%
#326
1%
b11000000 '
b00101111 (
#327
0%
#328
1%
b10110010 '
b00110100 (
#329
0%
#330
1%
b10100011 '
b00111001 (
#331
0%
#332
1%
b10010100 '
b00111110 (
#333
0%
#334
1%
b10000101 '
b01000011 (
#335
0%
#336
1%
b01110101 '
b01001000 (
#337
0%
#338
1%
b01100110 '
b01001101 (
#339
0%
#340
1%
b01010111 '
b01010010 (
#341
0%
#342
1%
b01001000 '
b01010111 (
#343
0%
#344
1%
b00111011 '
b01011100 (
#345
0%
#346
1%
b00101110 '
b01100001 (
#347
0%
#348
1%
b00100011 '
b01100110 (
#349
0%
#350
1%
b00011000 '
b01101011 (
#351
0%
#352
1%
b00010000 '
b01110000 (
#353
0%
#354
1%
b00001001 '
b01110101 (
#355
0%
#356
1%
b00000100 '
b01111010 (
#357
0%
#358
1%
b00000001 '
b01111111 (
#359
0%
#360
1%
b00000000 '
b10000100 (
#361
0%
#362
1%
b10001001 (
#363
0%
#364
1%
b00000011 '
b10001110 (
#365
0%
#366
1%
b00000111 '
b10010011 (
#367
0%
#368
1%
b00001101 '
b10011000 (
#369
0%
#370
1%
b00010101 '
b10011101 (
#371
0%
#372
1%
b00011110 '
b10100010 (
#373
0%
#374
1%
b00101001 '
b10100111 (
#375
0%
#376
1%
b00110101 '
b10101100 (
#377
0%
#378
1%
b01000011 '
b10110001 (
#379
0%
#380
1%
b01010001 '
b10110110 (
#381
0%
#382
1%
b01100000 '
b10111011 (
#383
0%
#384
1%
b01101111 '
b11000000 (
#385
0%
#386
1%
b01111111 '
b11000101 (
#387
0%
#388
1%
b10001110 '
b11001010 (
#389
0%
#390
1%
b10011101 '
b11001111 (
#391
0%
#392
1%
b10101100 '
b11010100 (
#393
0%
#394
1%
b10111010 '
b11011001 (
#395
0%
#396
1%
b11001000 '
b11011110 (
#397
0%
#398
1%
b11010100 '
b11100011 (
#399
0%
#400
1%
b11011111 '
b11101000 (
#401
0%
#402
1%
b11101000 '
b11101101 (
#403
0%
#404
1%
b11110000 '
b11110010 (
#405
0%
#406
1%
b11110110 '
b11110111 (
#407
0%
#408
1%
b11111010 '
b11111100 (
#409
0%
#410
1%
b11111101 '
b00000001 (
#411
0%
#412
1%
b00000110 (
#413
0%
#414
1%
b11111100 '
b00001011 (
#415
0%
#416
1%
b11111001 '
b00010000 (
#417
0%
#418
1%
b11110100 '
b00010101 (
#419
0%
#420
1%
b11101101 '
b00011010 (
#421
0%
#422
1%
b11100101 '
b00011111 (
#423
0%
#424
1%
b11011010 '
b00100100 (
#425
0%
#426
1%
b11001111 '
b00101001 (
#427
0%
#428
1%
b11000010 '
b00101110 (
#429
0%
#430
1%
b10110101 '
b00110011 (
#431
0%
#432
1%
b10100110 '
b00111000 (
#433
0%
#434
1%
b10010111 '
b00111101 (
#435
0%
#436
1%
b10001000 '
b01000010 (
#437
0%
#438
1%
b01111000 '
b01000111 (
#439
0%
#440
1%
b01101001 '
b01001100 (
#441
0%
#442
1%
b01011010 '
b01010001 (
#443
0%
#444
1%
b01001011 '
b01010110 (
#445
0%
#446
1%
b00111101 '
b01011011 (
#447
0%
#448
1%
b00110000 '
b01100000 (
#449
0%
#450
1%
b00100101 '
b01100101 (
#451
0%
#452
1%
b00011010 '
b01101010 (
#453
0%
#454
1%
b00010010 '
b01101111 (
#455
0%
#456
1%
b00001010 '
b01110100 (
#457
0%
#458
1%
b00000101 '
b01111001 (
#459
0%
#460
1%
b00000001 '
b01111110 (
#461
0%
#462
1%
b00000000 '
b10000011 (
#463
0%
#464
1%
b10001000 (
#465
0%
#466
1%
b00000010 '
b10001101 (
#467
0%
#468
1%
b00000110 '
b10010010 (
#469
0%
#470
1%
b00001100 '
b10010111 (
#471
0%
#472
1%
b00010011 '
b10011100 (
#473
0%
#474
1%
b00011100 '
b10100001 (
#475
0%
#476
1%
b00100111 '
b10100110 (
#477
0%
#478
1%
b00110011 '
b10101011 (
#479
0%
#480
1%
b01000000 '
b10110000 (
#481
0%
#482
1%
b01001110 '
b10110101 (
#483
0%
#484
1%
b01011101 '
b10111010 (
#485
0%
#486
1%
b01101100 '
b10111111 (
#487
0%
#488
1%
b01111011 '
b11000100 (
#489
0%
#490
1%
b10001011 '
b11001001 (
#491
0%
#492
1%
b10011010 '
b11001110 (
#493
0%
#494
1%
b10101001 '
b11010011 (
#495
0%
#496
1%
b10111000 '
b11011000 (
#497
0%
#498
1%
b11000101 '
b11011101 (
#499
0%
#500
1%
b11010001 '
b11100010 (
#501
0%
#502
1%
b11011101 '
b11100111 (
#503
0%
#504
1%
b11100110 '
b11101100 (
#505
0%
#506
1%
b11101111 '
b11110001 (
#507
0%
#508
1%
b11110101 '
b11110110 (
#509
0%
#510
1%
b11111010 '
b11111011 (
#511
0%
#512
1%
b11111101 '
b00000000 (
#513
0%
#514
1%
b11111110 '
b00000101 (
#515
0%
#516
1%
b11111101 '
b00001010 (
#517
0%
#518
1%
b11111010 '
b00001111 (
#519
0%
#520
1%
b11110101 '
b00010100 (
#521
0%
#522
1%
b11101111 '
b00011001 (
#523
0%
#524
1%
b11100110 '
b00011110 (
#525
0%
#526
1%
b11011101 '
b00100011 (
#527
0%
#528
1%
b11010001 '
b00101000 (
#529
0%
#530
1%
b11000101 '
b00101101 (
#531
0%
#532
1%
b10111000 '
b00110010 (
#533
0%
#534
1%
b10101001 '
b00110111 (
#535
0%
#536
1%
b10011010 '
b00111100 (
#537
0%
#538
1%
b10001011 '
b01000001 (
#539
0%
#540
1%
b01111011 '
b01000110 (
#541
0%
#542
1%
b01101100 '
b01001011 (
#543
0%
#544
1%
b01011101 '
b01010000 (
#545
0%
#546
1%
b01001110 '
b01010101 (
#547
0%
#548
1%
b01000000 '
b01011010 (
#549
0%
#550
1%
b00110011 '
b01011111 (
#551
0%
#552
1%
b00100111 '
b01100100 (
#553
0%
#554
1%
b00011100 '
b01101001 (
#555
0%
#556
1%
b00010011 '
b01101110 (
#557
0%
#558
1%
b00001100 '
b01110011 (
#559
0%
#560
1%
b00000110 '
b01111000 (
#561
0%
#562
1%
b00000010 '
b01111101 (
#563
0%
#564
1%
b00000000 '
b10000010 (
#565
0%
#566
1%
b10000111 (
#567
0%
#568
1%
b00000001 '
b10001100 (
#569
0%
#570
1%
b00000101 '
b10010001 (
#571
0%
#572
1%
b00001010 '
b10010110 (
#573
0%
#574
1%
b00010010 '
b10011011 (
#575
0%
#576
1%
b00011010 '
b10100000 (
#577
0%
#578
1%
b00100101 '
b10100101 (
#579
0%
#580
1%
b00110000 '
b10101010 (
#581
0%
#582
1%
b00111101 '
b10101111 (
#583
0%
#584
1%
b01001011 '
b10110100 (
#585
0%
#586
1%
b01011010 '
b10111001 (
#587
0%
#588
1%
b01101001 '
b10111110 (
#589
0%
#590
1%
b01111000 '
b11000011 (
#591
0%
#592
1%
b10001000 '
b11001000 (
#593
0%
#594
1%
b10010111 '
b11001101 (
#595
0%
#596
1%
b10100110 '
b11010010 (
#597
0%
#598
1%
b10110101 '
b11010111 (
#599
0%
#600
1%
b11000010 '
b11011100 (
#601
0%
#602
1%
b11001111 '
b11100001 (
#603
0%
#604
1%
b11011010 '
b11100110 (
#605
0%
#606
1%
b11100101 '
b11101011 (
#607
0%
#608
1%
b11101101 '
b11110000 (
#609
0%
#610
1%
b11110100 '
b11110101 (
#611
0%
#612
1%
b11111001 '
b11111010 (
#613
0%
#614
1%
b11111100 '
b11111111 (
#615
0%
#616
1%
b11111101 '
b00000100 (
#617
0%
#618
1%
b00001001 (
#619
0%
#620
1%
b11111010 '
b00001110 (
#621
0%
#622
1%
b11110110 '
b00010011 (
#623
0%
#624
1%
b11110000 '
b00011000 (
#625
0%
#626
1%
b11101000 '
b00011101 (
#627
0%
#628
1%
b11011111 '
b00100010 (
#629
0%
#630
1%
b11010100 '
b00100111 (
#631
0%
#632
1%
b11001000 '
b00101100 (
#633
0%
#634
1%
b10111010 '
b00110001 (
#635
0%
#636
1%
b10101100 '
b00110110 (
#637
0%
#638
1%
b10011101 '
b00111011 (
#639
0%
#640
1%
b10001110 '
b01000000 (
#641
0%
#642
1%
b01111110 '
b01000101 (
#643
0%
#644
1%
b01101111 '
b01001010 (
#645
0%
#646
1%
b01100000 '
b01001111 (
#647
0%
#648
1%
b01010001 '
b01010100 (
#649
0%
#650
1%
b01000011 '
b01011001 (
#651
0%
#652
1%
b00110101 '
b01011110 (
#653
0%
#654
1%
b00101001 '
b01100011 (
#655
0%
#656
1%
b00011110 '
b01101000 (
#657
0%
#658
1%
b00010101 '
b01101101 (
#659
0%
#660
1%
b00001101 '
b01110010 (
#661
0%
#662
1%
b00000111 '
b01110111 (
#663
0%
#664
1%
b00000011 '
b01111100 (
#665
0%
#666
1%
b00000000 '
b10000001 (
#667
0%
#668
1%
b10000110 (
#669
0%
#670
1%
b00000001 '
b10001011 (
#671
0%
#672
1%
b00000100 '
b10010000 (
#673
0%
#674
1%
b00001001 '
b10010101 (
#675
0%
#676
1%
b00010000 '
b10011010 (
#677
0%
#678
1%
b00011000 '
b10011111 (
#679
0%
#680
1%
b00100011 '
b10100100 (
#681
0%
#682
1%
b00101110 '
b10101001 (
#683
0%
#684
1%
b00111011 '
b10101110 (
#685
0%
#686
1%
b01001000 '
b10110011 (
#687
0%
#688
1%
b01010111 '
b10111000 (
#689
0%
#690
1%
b01100110 '
b10111101 (
#691
0%
#692
1%
b01110101 '
b11000010 (
#693
0%
#694
1%
b10000101 '
b11000111 (
#695
0%
#696
1%
b10010100 '
b11001100 (
#697
0%
#698
1%
b10100011 '
b11010001 (
#699
0%
#700
1%
b10110010 '
b11010110 (
#701
0%
#702
1%
b11000000 '
b11011011 (
#703
0%
#704
1%
b11001101 '
b11100000 (
#705
0%
#706
1%
b11011000 '
b11100101 (
#707
0%
#708
1%
b11100011 '
b11101010 (
#709
0%
#710
1%
b11101011 '
b11101111 (
#711
0%
#712
1%
b11110011 '
b11110100 (
#713
0%
#714
1%
b11111000 '
b11111001 (
#715
0%
#716
1%
b11111100 '
b11111110 (
#717
0%
#718
1%
b11111101 '
b00000011 (
#719
0%
#720
1%
b00001000 (
#721
0%
#722
1%
b11111011 '
b00001101 (
#723
0%
#724
1%
b11110111 '
b00010010 (
#725
0%
#726
1%
b11110001 '
b00010111 (
#727
0%
#728
1%
b11101010 '
b00011100 (
#729
0%
#730
1%
b11100001 '
b00100001 (
#731
0%
#732
1%
b11010110 '
b00100110 (
#733
0%
#734
1%
b11001010 '
b00101011 (
#735
0%
#736
1%
b10111101 '
b00110000 (
#737
0%
#738
1%
b10101111 '
b00110101 (
#739
0%
#740
1%
b10100000 '
b00111010 (
#741
0%
#742
1%
b10010001 '
b00111111 (
#743
0%
#744
1%
b10000010 '
b01000100 (
#745
0%
#746
1%
b01110010 '
b01001001 (
#747
0%
#748
1%
b01100011 '
b01001110 (
#749
0%
#750
1%
b01010100 '
b01010011 (
#751
0%
#752
1%
b01000101 '
b01011000 (
#753
0%
#754
1%
b00111000 '
b01011101 (
#755
0%
#756
1%
b00101100 '
b01100010 (
#757
0%
#758
1%
b00100000 '
b01100111 (
#759
0%
#760
1%
b00010111 '
b01101100 (
#761
0%
#762
1%
b00001110 '
b01110001 (
#763
0%
#764
1%
b00001000 '
b01110110 (
#765
0%
#766
1%
b00000011 '
b01111011 (
#767
0%
#768
1%
b00000000 '
b10000000 (
#769
0%
#770
1%
b10000101 (
#771
0%
#772
1%
b10001010 (
#773
0%
#774
1%
b00000011 '
b10001111 (
#775
0%
#776
1%
b00001000 '
b10010100 (
#777
0%
#778
1%
b00001110 '
b10011001 (
#779
0%
#780
1%
b00010111 '
b10011110 (
#781
0%
#782
1%
b00100000 '
b10100011 (
#783
0%
#784
1%
b00101100 '
b10101000 (
#785
0%
#786
1%
b00111000 '
b10101101 (
#787
0%
#788
1%
b01000101 '
b10110010 (
#789
0%
#790
1%
b01010100 '
b10110111 (
#791
0%
#792
1%
b01100011 '
b10111100 (
#793
0%
#794
1%
b01110010 '
b11000001 (
#795
0%
#796
1%
b10000010 '
b11000110 (
#797
0%
#798
1%
b10010001 '
b11001011 (
#799
0%
#800
1%
b10100000 '
b11010000 (
#801
0%
#802
1%
b10101111 '
b11010101 (
#803
0%
#804
1%
b10111101 '
b11011010 (
#805
0%
#806
1%
b11001010 '
b11011111 (
#807
0%
#808
1%
b11010110 '
b11100100 (
#809
0%
#810
1%
b11100001 '
b11101001 (
#811
0%
#812
1%
b11101010 '
b11101110 (
#813
0%
#814
1%
b11110001 '
b11110011 (
#815
0%
#816
1%
b11110111 '
b11111000 (
#817
0%
#818
1%
b11111011 '
b11111101 (
#819
0%
#820
1%
b11111101 '
b00000010 (
#821
0%
#822
1%
b00000111 (
#823
0%
#824
1%
b11111100 '
b00001100 (
#825
0%
#826
1%
b11111000 '
b00010001 (
#827
0%
#828
1%
b11110011 '
b00010110 (
#829
0%
#830
1%
b11101011 '
b00011011 (
#831
0%
#832
1%
b11100011 '
b00100000 (
#833
0%
#834
1%
b11011000 '
b00100101 (
#835
0%
#836
1%
b11001101 '
b00101010 (
#837
0%
#838
1%
b11000000 '
b00101111 (
#839
0%
#840
1%
b10110010 '
b00110100 (
#841
0%
#842
1%
b10100011 '
b00111001 (
#843
0%
#844
1%
b10010100 '
b00111110 (
#845
0%
#846
1%
b10000101 '
b01000011 (
#847
0%
#848
1%
b01110101 '
b01001000 (
#849
0%
#850
1%
b01100110 '
b01001101 (
#851
0%
#852
1%
b01010111 '
b01010010 (
#853
0%
#854
1%
b01001000 '
b01010111 (
#855
0%
#856
1%
b00111011 '
b01011100 (
#857
0%
#858
1%
b00101110 '
b01100001 (
#859
0%
#860
1%
b00100011 '
b01100110 (
#861
0%
#862
1%
b00011000 '
b01101011 (
#863
0%
#864
1%
b00010000 '
b01110000 (
#865
0%
#866
1%
b00001001 '
b01110101 (
#867
0%
#868
1%
b00000100 '
b01111010 (
#869
0%
#870
1%
b00000001 '
b01111111 (
#871
0%
#872
1%
b00000000 '
b10000100 (
#873
0%
#874
1%
b10001001 (
#875
0%
#876
1%
b00000011 '
b10001110 (
#877
0%
#878
1%
b00000111 '
b10010011 (
#879
0%
#880
1%
b00001101 '
b10011000 (
#881
0%
#882
1%
b00010101 '
b10011101 (
#883
0%
#884
1%
b00011110 '
b10100010 (
#885
0%
#886
1%
b00101001 '
b10100111 (
#887
0%
#888
1%
b00110101 '
b10101100 (
#889
0%
#890
1%
b01000011 '
b10110001 (
#891
0%
#892
1%
b01010001 '
b10110110 (
#893
0%
#894
1%
b01100000 '
b10111011 (
#895
0%
#896
1%
b01101111 '
b11000000 (
#897
0%
#898
1%
b01111111 '
b11000101 (
#899
0%
#900
1%
b10001110 '
b11001010 (
#901
0%
#902
1%
b10011101 '
b11001111 (
#903
0%
#904
1%
b10101100 '
b11010100 (
#905
0%
#906
1%
b10111010 '
b11011001 (
#907
0%
#908
1%
b11001000 '
b11011110 (
#909
0%
#910
1%
b11010100 '
b11100011 (
#911
0%
#912
1%
b11011111 '
b11101000 (
#913
0%
#914
1%
b11101000 '
b11101101 (
#915
0%
#916
1%
b11110000 '
b11110010 (
#917
0%
#918
1%
b11110110 '
b11110111 (
#919
0%
#920
1%
b11111010 '
b11111100 (
#921
0%
#922
1%
b11111101 '
b00000001 (
#923
0%
#924
1%
b00000110 (
#925
0%
#926
1%
b11111100 '
b00001011 (
#927
0%
#928
1%
b11111001 '
b00010000 (
#929
0%
#930
1%
b11110100 '
b00010101 (
#931
0%
#932
1%
b11101101 '
b00011010 (
#933
0%
#934
1%
b11100101 '
b00011111 (
#935
0%
#936
1%
b11011010 '
b00100100 (
#937
0%
#938
1%
b11001111 '
b00101001 (
#939
0%
#940
1%
b11000010 '
b00101110 (
#941
0%
#942
1%
b10110101 '
b00110011 (
#943
0%
#944
1%
b10100110 '
b00111000 (
#945
0%
#946
1%
b10010111 '
b00111101 (
#947
0%
#948
1%
b10001000 '
b01000010 (
#949
0%
#950
1%
b01111000 '
b01000111 (
#951
0%
#952
1%
b01101001 '
b01001100 (
#953
0%
#954
1%
b01011010 '
b01010001 (
#955
0%
#956
1%
b01001011 '
b01010110 (
#957
0%
#958
1%
b00111101 '
b01011011 (
#959
0%
#960
1%
b00110000 '
b01100000 (
#961
0%
#962
1%
b00100101 '
b01100101 (
#963
0%
#964
1%
b00011010 '
b01101010 (
#965
0%
#966
1%
b00010010 '
b01101111 (
#967
0%
#968
1%
b00001010 '
b01110100 (
#969
0%
#970
1%
b00000101 '
b01111001 (
#971
0%
#972
1%
b00000001 '
b01111110 (
#973
0%
#974
1%
b00000000 '
b10000011 (
#975
0%
#976
1%
b10001000 (
#977
0%
#978
1%
b00000010 '
b10001101 (
#979
0%
#980
1%
b00000110 '
b10010010 (
#981
0%
#982
1%
b00001100 '
b10010111 (
#983
0%
#984
1%
b00010011 '
b10011100 (
#985
0%
#986
1%
b00011100 '
b10100001 (
#987
0%
#988
1%
b00100111 '
b10100110 (
#989
0%
#990
1%
b00110011 '
b10101011 (
#991
0%
#992
1%
b01000000 '
b10110000 (
#993
0%
#994
1%
b01001110 '
b10110101 (
#995
0%
#996
1%
b01011101 '
b10111010 (
#997
0%
#998
1%
b01101100 '
b10111111 (
#999
0%
#1000
1%
b01111011 '
b11000100 (
#1001
0%
#1002
1%
b10001011 '
b11001001 (
#1003
0%
#1004
1%
b10011010 '
b11001110 (
#1005
0%
#1006
1%
b10101001 '
b11010011 (
#1007
0%
#1008
1%
b10111000 '
b11011000 (
#1009
0%
#1010
1%
b11000101 '
b11011101 (
#1011
0%
#1012
1%
b11010001 '
b11100010 (
#1013
0%
#1014
1%
b11011101 '
b11100111 (
#1015
0%
#1016
1%
b11100110 '
b11101100 (
#1017
0%
#1018
1%
b11101111 '
b11110001 (
#1019
0%
#1020
1%
b11110101 '
b11110110 (
#1021
0%
#1022
1%
b11111010 '
b11111011 (
#1023
0%
#1024
1%
b11111101 '
b00000000 (
#1025
0%
#1026
1%
b11111110 '
b00000101 (
#1027
0%
#1028
1%
b11111101 '
b00001010 (
#1029
0%
#1030
1%
b11111010 '
b00001111 (
#1031
0%
#1032
1%
b11110101 '
b00010100 (
#1033
0%
#1034
1%
b11101111 '
b00011001 (
#1035
0%
#1036
1%
b11100110 '
b00011110 (
#1037
0%
#1038
1%
b11011101 '
b00100011 (
#1039
0%
#1040
1%
b11010001 '
b00101000 (
#1041
0%
#1042
1%
b11000101 '
b00101101 (
#1043
0%
#1044
1%
b10111000 '
b00110010 (
#1045
0%
#1046
1%
b10101001 '
b00110111 (
#1047
0%
#1048
1%
b10011010 '
b00111100 (
#1049
0%
#1050
1%
b10001011 '
b01000001 (
#1051
0%
#1052
1%
b01111011 '
b01000110 (
#1053
0%
#1054
1%
b01101100 '
b01001011 (
#1055
0%
#1056
1%
b01011101 '
b01010000 (
